mcp_pdf_chroma/__init__.py
mcp_pdf_chroma/config.py
mcp_pdf_chroma/metadata_store.py
mcp_pdf_chroma/pdf_processor.py
mcp_pdf_chroma/server.py
mcp_pdf_chroma/vector_db.py
mcp_pdf_chroma-1.0.1.dist-info/licenses/LICENSE
mcp_pdf_chroma-1.0.1.dist-info/METADATA
mcp_pdf_chroma-1.0.1.dist-info/WHEEL
mcp_pdf_chroma-1.0.1.dist-info/entry_points.txt
mcp_pdf_chroma-1.0.1.dist-info/top_level.txt
mcp_pdf_chroma-1.0.1.dist-info/RECORD
