Metadata-Version: 2.4
Name: mcp-pdf-chroma
Version: 1.0.1
Summary: MCP server for PDF processing and semantic search with ChromaDB
Author-email: Your Name <your.email@example.com>
License: MIT
Project-URL: Homepage, https://github.com/yourusername/mcp_pdf_chroma
Project-URL: Repository, https://github.com/yourusername/mcp_pdf_chroma
Project-URL: Issues, https://github.com/yourusername/mcp_pdf_chroma/issues
Project-URL: Documentation, https://github.com/yourusername/mcp_pdf_chroma#readme
Keywords: mcp,pdf,chromadb,embeddings,semantic-search
Classifier: Development Status :: 4 - Beta
Classifier: Intended Audience :: Developers
Classifier: Programming Language :: Python :: 3
Classifier: Programming Language :: Python :: 3.10
Classifier: Programming Language :: Python :: 3.11
Classifier: Programming Language :: Python :: 3.12
Requires-Python: >=3.10
License-File: LICENSE
Requires-Dist: mcp>=1.0.0
Requires-Dist: langchain>=0.1.0
Requires-Dist: langchain-community>=0.0.10
Requires-Dist: pypdf>=3.17.0
Requires-Dist: chromadb>=0.4.22
Requires-Dist: sentence-transformers>=2.2.2
Requires-Dist: torch>=2.0.0
Requires-Dist: requests>=2.31.0
Requires-Dist: python-dotenv>=1.0.0
Provides-Extra: dev
Requires-Dist: pytest>=7.0.0; extra == "dev"
Requires-Dist: pytest-asyncio>=0.21.0; extra == "dev"
Requires-Dist: black>=23.0.0; extra == "dev"
Requires-Dist: mypy>=1.0.0; extra == "dev"
Dynamic: license-file
